rtquery/__init__.py
rtquery/_version.py
rtquery/query.py
rtquery/tree.py
rtquery/utils/__init__.py
rtquery/utils/ast.py
rtquery/utils/consts.py
rtquery/utils/grammatic.bnf
rtquery/utils/interpreter.py
rtquery/utils/lexer.py
rtquery/utils/operations.py
rtquery/utils/parser.py
rtquery/utils/query.py
rtquery/utils/visitors.py
rtquery-0.10.1.dist-info/DESCRIPTION.rst
rtquery-0.10.1.dist-info/METADATA
rtquery-0.10.1.dist-info/RECORD
rtquery-0.10.1.dist-info/WHEEL
rtquery-0.10.1.dist-info/metadata.json
rtquery-0.10.1.dist-info/top_level.txt
tests/__init__.py
tests/test_q.py
tests/test_version.py
tests/utils/__init__.py
tests/utils/test_ast.py
tests/utils/test_interpreter.py
tests/utils/test_lexer.py
tests/utils/test_parser.py
tests/utils/test_query.py
tests/utils/test_visitors.py
