Metadata-Version: 2.0
Name: rtquery
Version: 0.10.1
Summary: Request Tracker Querying Library
Home-page: https://github.com/tarvitz/rtquery
Author: Nickolas Fox
Author-email: tarvitz@blacklibrary.ru
License: UNKNOWN
Keywords: request tracker query lib
Platform: any
Classifier: Development Status :: 4 - Beta
Classifier: Environment :: Other Environment
Classifier: Intended Audience :: Developers
Classifier: License :: OSI Approved :: BSD License
Classifier: Operating System :: POSIX
Classifier: Programming Language :: Python :: 3.4
Classifier: Programming Language :: Python :: 3.5
Classifier: Programming Language :: Python :: 3.6
Classifier: Programming Language :: Python :: 3.7
Classifier: Programming Language :: Python :: 3 :: Only
Classifier: Programming Language :: Python :: Implementation :: CPython
Classifier: Topic :: Software Development :: Libraries
Requires-Python: >=3
